drf_spectacular/__init__.py
drf_spectacular/apps.py
drf_spectacular/authentication.py
drf_spectacular/checks.py
drf_spectacular/drainage.py
drf_spectacular/extensions.py
drf_spectacular/generators.py
drf_spectacular/helpers.py
drf_spectacular/hooks.py
drf_spectacular/openapi.py
drf_spectacular/plumbing.py
drf_spectacular/py.typed
drf_spectacular/renderers.py
drf_spectacular/serializers.py
drf_spectacular/settings.py
drf_spectacular/types.py
drf_spectacular/utils.py
drf_spectacular/views.py
drf_spectacular/contrib/__init__.py
drf_spectacular/contrib/django_filters.py
drf_spectacular/contrib/django_oauth_toolkit.py
drf_spectacular/contrib/djangorestframework_camel_case.py
drf_spectacular/contrib/pydantic.py
drf_spectacular/contrib/rest_auth.py
drf_spectacular/contrib/rest_framework.py
drf_spectacular/contrib/rest_framework_dataclasses.py
drf_spectacular/contrib/rest_framework_gis.py
drf_spectacular/contrib/rest_framework_jwt.py
drf_spectacular/contrib/rest_framework_recursive.py
drf_spectacular/contrib/rest_framework_simplejwt.py
drf_spectacular/contrib/rest_polymorphic.py
drf_spectacular/management/__init__.py
drf_spectacular/management/commands/__init__.py
drf_spectacular/management/commands/spectacular.py
drf_spectacular/templates/drf_spectacular/redoc.html
drf_spectacular/templates/drf_spectacular/swagger_ui.html
drf_spectacular/templates/drf_spectacular/swagger_ui.js
drf_spectacular/validation/__init__.py
drf_spectacular/validation/openapi_3_0_schema.json
drf_spectacular/validation/openapi_3_1_schema.json
drf_spectacular-0.27.1.dist-info/LICENSE
drf_spectacular-0.27.1.dist-info/METADATA
drf_spectacular-0.27.1.dist-info/WHEEL
drf_spectacular-0.27.1.dist-info/top_level.txt
drf_spectacular-0.27.1.dist-info/RECORD
