Metadata-Version: 2.1
Name: drf-spectacular
Version: 0.27.1
Summary: Sane and flexible OpenAPI 3 schema generation for Django REST framework
Home-page: https://github.com/tfranzel/drf-spectacular
Author: T. Franzel
Author-email: tfranzel@gmail.com
License: BSD
Project-URL: Source, https://github.com/tfranzel/drf-spectacular
Project-URL: Documentation, https://drf-spectacular.readthedocs.io
Classifier: Development Status :: 5 - Production/Stable
Classifier: Environment :: Web Environment
Classifier: Framework :: Django
Classifier: Framework :: Django :: 2.2
Classifier: Framework :: Django :: 3.2
Classifier: Framework :: Django :: 4.0
Classifier: Framework :: Django :: 4.1
Classifier: Framework :: Django :: 4.2
Classifier: Intended Audience :: Developers
Classifier: License :: OSI Approved :: BSD License
Classifier: Operating System :: OS Independent
Classifier: Natural Language :: English
Classifier: Programming Language :: Python :: 3
Classifier: Programming Language :: Python :: 3.6
Classifier: Programming Language :: Python :: 3.7
Classifier: Programming Language :: Python :: 3.8
Classifier: Programming Language :: Python :: 3.9
Classifier: Programming Language :: Python :: 3.10
Classifier: Programming Language :: Python :: 3.11
Classifier: Programming Language :: Python :: 3.12
Classifier: Topic :: Internet :: WWW/HTTP
Classifier: Topic :: Documentation
Classifier: Topic :: Software Development :: Code Generators
Requires-Python: >=3.6
License-File: LICENSE
Requires-Dist: Django>=2.2
Requires-Dist: djangorestframework>=3.10.3
Requires-Dist: uritemplate>=2.0.0
Requires-Dist: PyYAML>=5.1
Requires-Dist: jsonschema>=2.6.0
Requires-Dist: inflection>=0.3.1
Requires-Dist: typing-extensions; python_version < "3.10"
Provides-Extra: offline
Requires-Dist: drf-spectacular-sidecar; extra == "offline"
Provides-Extra: sidecar
Requires-Dist: drf-spectacular-sidecar; extra == "sidecar"
